{
    "File": "Файл",
    "I have the .hex file": "У меня есть файл .hex",
    "I don't have the .hex file": "У меня нет файла .hex",
    "Do you have the .hex file?": "У вас есть файл .hex?",
    "Choose device": "Выберите устройство",
    "Devices": "Yстройства",
    "Choose file": "Выберите файл",
    "Choose baudrate": "Выберите скорость передачи",
    "Choose port": "Выберите порт",
    "Flashing": "мигающий",
    "Flash!": "Вспышка!",
    "Confirm": "Подтверждение",
    "No ports": "Нет портов",
    "Other": "Другой",
    "RAMPS-based": "RAMPS на основе",
    "We are working on it": "Мы работаем над этим",
    "Close": "",
    "Something went wrong!": "",
    "Abort": "",
    "Choose the firmware language": "",
    "Sensor": "",
    "ABL sensor": "",
    "Here you can find further tips how to solve that problem:": "",
    "answer_1": "",
    "question_2": "",
    "answer_2": "",
    "Version": "",
    "Created by Garage Makezone": ""
}